matfleet/__init__.py
matfleet/constant.py
matfleet/get_doc.py
matfleet/core/__init__.py
matfleet/core/general_plot/__init__.py
matfleet/core/general_plot/alkuser_hist.py
matfleet/core/general_plot/data_smooth.py
matfleet/core/mpa_base/__init__.py
matfleet/core/mpa_base/alkemie_scmap.py
matfleet/scripts/__init__.py
matfleet/scripts/auxbool_argparse.py
matfleet/scripts/dcjson.py
matfleet/scripts/get_TexTable_fromCSV.py
matfleet/scripts/io_file.py
matfleet/scripts/learn_dcjson.py
matfleet/scripts/plt_for_pm.py
matfleet/scripts/plt_periodic.py
matfleet/scripts/seaborn_multi_subplot.py
matfleet/scripts/test_pathlib.py
matfleet/scripts/tools.py
matfleet/scripts/unit_test.py
matfleet/scripts/unit_test/__init__.py
matfleet/scripts/unit_test/test_array2d.py
matfleet/tools/__init__.py
matfleet/tools/weichat_dat.py
matfleet/utilities/__init__.py
matfleet/utilities/auxbool_argparse.py
matfleet/utilities/constant.py
matfleet/utilities/encryption.py
matfleet/utilities/get_help_doc.py
matfleet/utilities/mang_jpg2pdf.py
matfleet/utilities/mconfig.py
matfleet/utilities/mjson.py
matfleet/utilities/mlog.py
matfleet/utilities/mrelated_files.py
matfleet/utilities/mshell.py
matfleet/utilities/msimple_func.py
matfleet/utilities/mtime.py
matfleet/utilities/mtype.py
matfleet/utilities/myaml.py
matfleet/utilities/test.py
matfleet/vasp/__init__.py
matfleet/vasp/bppb.py
matfleet/vasp/poscar.py
matfleet/vasp/tmp.py
matfleet/vasp/vasp_band.py
matfleet/vasp/vasp_dos.py
matfleet/vasp/xdatcar.py
matfleet/vasp/xsf.py
matfleet/vasp/unit_test/__init__.py
matfleet/vasp/unit_test/test_plt.py
matfleet/vasp/unit_test/test_poscar.py
matfleet/vasp/unit_test/test_xdatcar.py
matfleet/vasp/unit_test/test_xsf.py
matfleet-0.0.7.dist-info/METADATA
matfleet-0.0.7.dist-info/WHEEL
matfleet-0.0.7.dist-info/entry_points.txt
matfleet-0.0.7.dist-info/top_level.txt
matfleet-0.0.7.dist-info/RECORD
