Metadata-Version: 2.1
Name: matfleet
Version: 0.0.7
Summary: test
Home-page: https://gitee.com/alkemiems/matfleet
Author: Guanjie Wang
Author-email: gjwang@buaa.edu.cn
License: MIT
